{
  "advancement": "minecraft:adventure/adventuring_time",
  "modifiers": [
    {
      "type": "criteria",
      "config": {
        "mode": "modify",
        "criteria": {
          "environmental:marsh": {
            "trigger": "minecraft:location",
            "conditions": {
              "location": {
                "biome": "environmental:marsh"
              }
            }
          },
          "environmental:mushroom_marsh": {
            "trigger": "minecraft:location",
            "conditions": {
              "location": {
                "biome": "environmental:mushroom_marsh"
              }
            }
          },
          "environmental:blossom_woods": {
            "trigger": "minecraft:location",
            "conditions": {
              "location": {
                "biome": "environmental:blossom_woods"
              }
            }
          },
          "environmental:blossom_hills": {
            "trigger": "minecraft:location",
            "conditions": {
              "location": {
                "biome": "environmental:blossom_hills"
              }
            }
          },
          "environmental:blossom_highlands": {
            "trigger": "minecraft:location",
            "conditions": {
              "location": {
                "biome": "environmental:blossom_highlands"
              }
            }
          },
          "environmental:blossom_valleys": {
            "trigger": "minecraft:location",
            "conditions": {
              "location": {
                "biome": "environmental:blossom_valleys"
              }
            }
          }
        },
        "requirements": [
          [
            "environmental:marsh"
          ],
          [
            "environmental:mushroom_marsh"
          ],
          [
            "environmental:blossom_woods"
          ],
          [
            "environmental:blossom_hills"
          ],
          [
            "environmental:blossom_highlands"
          ],
          [
            "environmental:blossom_valleys"
          ]
        ]
      }
    }
  ]
}